langpy/__init__.py
langpy/auto.py
langpy/base.py
langpy/colab_lp.py
langpy/jupyter_lp.py
langpy/data_loader/__init__.py
langpy/data_loader/csv_loader.py
langpy/data_loader/json_loader.py
langpy/data_loader/loader.py
langpy_notebook-0.4.dist-info/LICENSE
langpy_notebook-0.4.dist-info/METADATA
langpy_notebook-0.4.dist-info/WHEEL
langpy_notebook-0.4.dist-info/top_level.txt
langpy_notebook-0.4.dist-info/RECORD
