Metadata-Version: 2.1
Name: langpy-notebook
Version: 0.4
Summary: Chat in Python on IPython notebook.
Home-page: https://github.com/luohongyin/langpy-notebook
Author: Hongyin Luo
Author-email: hyluo@mit.edu
Classifier: Programming Language :: Python :: 3
Classifier: License :: OSI Approved :: MIT License
Classifier: Operating System :: OS Independent
License-File: LICENSE
Requires-Dist: IPython
Requires-Dist: notebook (==6.4.8)
